{
	"description": "项目配置文件",
	"packOptions": {
		"ignore": []
	},
	"setting": {
		"urlCheck": false,
		"es6": true,
		"postcss": true,
		"minified": true,
		"newFeature": true
	},
	"compileType": "miniprogram",
	"libVersion": "2.3.2",
	"appid": "wxd449244360c8ce45",
	"projectname": "pzhanxx",
	"debugOptions": {
		"hidedInDevtools": []
	},
	"isGameTourist": false,
	"condition": {
		"search": {
			"current": -1,
			"list": []
		},
		"conversation": {
			"current": -1,
			"list": []
		},
		"plugin": {
			"current": -1,
			"list": []
		},
		"game": {
			"currentL": -1,
			"list": []
		},
		"miniprogram": {
			"current": 1,
			"list": [
				{
					"id": 0,
					"name": "share",
					"pathName": "pages/me/share/share",
					"query": "share_id=3",
					"scene": "1008"
				},
				{
					"id": 1,
					"name": "shares",
					"pathName": "pages/index/index",
					"query": "id=3",
					"scene": "1044",
					"shareInfo": {
						"groupName": "测试模拟群0",
						"shareName": "bnhPLijVLlCb20O76QX0VJObf_33kg3GRweWxaIgGBQ@cr4dev",
						"shareKey": "TD_BdU1-KAH6QU1DXL_25-3nGr0NTG5jr5dfKGxhuIyTjm1GXYsZ0btdHoNt331a8f34dX0pFpaXxTsb5Vvs8Q~~"
					}
				}
			]
		}
	}
}